{
  "project_info": {
    "project_number": "88013717712",
    "project_id": "beerworld-a23b1",
    "storage_bucket": "beerworld-a23b1.appspot.com"
  },
  "client": [
    {
      "client_info": {
        "mobilesdk_app_id": "1:88013717712:android:cc08fb7a551461b0e15ed5",
        "android_client_info": {
          "package_name": "com.example.mobileappprod"
        }
      },
      "oauth_client": [],
      "api_key": [
        {
          "current_key": "AIzaSyBAR9QdY0MH7BcmYmaou8NJxgiEMMUEHB4"
        }
      ],
      "services": {
        "appinvite_service": {
          "other_platform_oauth_client": []
        }
      }
    }
  ],
  "configuration_version": "1"
}